{
    "version": "4.5.6",
    "flags": {},
    "shapes": [
        {
            "label": "main",
            "points": [
                [
                    212.81613123718387,
                    271.59945317840055
                ],
                [
                    735.0307587149691,
                    859.4326725905673
                ]
            ],
            "group_id": null,
            "shape_type": "rectangle",
            "labels": [],
            "flags": {}
        }
    ],
    "imagePath": "[가방] Fendi_라일락 가죽 미니백_1.jpg",
    "imageWidth": 900,
    "imageHeight": 900,
    "imageData": null
}